CHANGELOG.txt
LICENSE.txt
MANIFEST.in
README.md
requirements.txt
setup.cfg
setup.py
test_vm.py
variantmap_app.py
variantmap/__init__.py
variantmap/layout_helper.py
variantmap/variantmap.py
variantmap/version.py
variantmap.egg-info/PKG-INFO
variantmap.egg-info/SOURCES.txt
variantmap.egg-info/dependency_links.txt
variantmap.egg-info/requires.txt
variantmap.egg-info/top_level.txt
variantmap/assets/GitHub-Mark-Light-64px.png
variantmap/assets/base.css
variantmap/assets/dash-variant-map.css
variantmap/assets/demo-image.png
variantmap/assets/general-app-page.css
variantmap/assets/plotly-dash-bio-logo.png
variantmap/data/sample_data.h5