Metadata-Version: 2.1
Name: variantmap
Version: 1.0.2
Summary: Interactive heatmap for multi-sample structural variant analysis
Home-page: https://github.com/cytham/variantmap
Author: Tham Cheng Yong
Author-email: chengyong.tham@u.nus.edu
License: gpl-3.0
Download-URL: https://github.com/cytham/variantmap/releases
Keywords: variantmap,structural variant,multiple samples,variantbreak,nanovar,heatmap
Platform: UNKNOWN
Classifier: Operating System :: POSIX :: Linux
Classifier: Programming Language :: Python :: 3.6
Classifier: Programming Language :: Python :: 3.7
Classifier: License :: OSI Approved :: GNU General Public License v3 (GPLv3)
Classifier: Topic :: Scientific/Engineering :: Bio-Informatics
Requires-Python: >=3.6
